FortranBinary/FortranBinary.py
FortranBinary/__init__.py
FortranBinary-21.2.1.dist-info/LICENSE.txt
FortranBinary-21.2.1.dist-info/METADATA
FortranBinary-21.2.1.dist-info/WHEEL
FortranBinary-21.2.1.dist-info/top_level.txt
FortranBinary-21.2.1.dist-info/RECORD
